{
  "Routes": [
    {
      "UpstreamPathTemplate": "/api/User/Yey",
      "DownstreamPathTemplate": "/api/User/Yey",
      "UpstreamHttpMethod": [ "Post", "Get" ],
      "DownstreamScheme": "http",
      "DownstreamHostAndPorts": [
        {
          "Host": "localhost",
          "Port": 5156
        }
      ]
    },
    {
      "UpstreamPathTemplate": "/api/User/Register",
      "DownstreamPathTemplate": "/api/User/Register",
      "UpstreamHttpMethod": [ "Post"],
      "DownstreamScheme": "http",
      "DownstreamHostAndPorts": [
        {
          "Host": "localhost",
          "Port": 5156
        }
      ]
    },
    {
      "UpstreamPathTemplate": "/api/User/Login",
      "DownstreamPathTemplate": "/api/User/Login",
      "UpstreamHttpMethod": [ "Post"],
      "DownstreamScheme": "http",
      "DownstreamHostAndPorts": [
        {
          "Host": "localhost",
          "Port": 5156
        }
      ]
    }
  ]
}
